pytest_fixtures_fixtures/__init__.py
pytest_fixtures_fixtures/parametrize.py
pytest_fixtures_fixtures/protocols.py
pytest_fixtures_fixtures/py.typed
pytest_fixtures_fixtures/pytest_plugin.py
pytest_fixtures_fixtures-0.4.0.dist-info/WHEEL
pytest_fixtures_fixtures-0.4.0.dist-info/entry_points.txt
pytest_fixtures_fixtures-0.4.0.dist-info/METADATA
pytest_fixtures_fixtures-0.4.0.dist-info/RECORD
