Metadata-Version: 2.3
Name: pytest-fixtures-fixtures
Version: 0.4.0
Summary: Handy fixtues to access your fixtures from your _pytest_ tests.
Keywords: testing,pytest
Author: Antonio Feregrino
Author-email: Antonio Feregrino <antonio.feregrino@gmail.com>
License: MIT
Classifier: Development Status :: 4 - Beta
Classifier: Intended Audience :: Developers
Classifier: License :: OSI Approved :: MIT License
Classifier: Operating System :: OS Independent
Classifier: Programming Language :: Python :: 3
Classifier: Programming Language :: Python :: 3.10
Classifier: Programming Language :: Python :: 3.11
Classifier: Programming Language :: Python :: 3.12
Classifier: Programming Language :: Python :: 3.13
Classifier: Topic :: Software Development :: Testing
Classifier: Topic :: Software Development :: Libraries :: Python Modules
Classifier: Topic :: Text Processing :: Markup
Classifier: Topic :: Utilities
Classifier: Typing :: Typed
Requires-Dist: pytest>=8.4.1
Maintainer: Antonio Feregrino
Maintainer-email: Antonio Feregrino <antonio.feregrino@gmail.com>
Requires-Python: >=3.10
Project-URL: Homepage, https://github.com/fferegrino/pytest-fixtures-fixtures
Project-URL: Issues, https://github.com/fferegrino/pytest-fixtures-fixtures/issues
Project-URL: Repository, https://github.com/fferegrino/pytest-fixtures-fixtures.git
